Metadata-Version: 1.1
Name: pygssw
Version: 0.0.5
Summary: Wrapper around GSSW, making it possible to align reads to graphs from python using GSSW
Home-page: http://github.com/uio-bmi/pygssw
Author: Ivar Grytten
Author-email: ivargry@ifi.uio.no
License: MIT
Platform: UNKNOWN
Classifier: Programming Language :: Python :: 3
